ass_2/ass_2_tb.v
module ass_2_tb;
wire [15:0] z;
reg [3:0]rs1,rs2,rd,func;
reg [7:0]addr;
reg clk1,clk2;
integer k;
ass_2 MYPIPE (z,rs1,rs2,rd,addr,func,clk1,clk2);
initial 
 begin
  clk1=0; clk2=0;
  repeat(20)
   begin
   #5 clk1=1; #5 clk1=0;
   #5 clk2=1; #5 clk2=0;
   end
 end
initial
 for( k=0;k<16;k=k+1)
   MYPIPE.regbank[k]=k;

initial
 begin
  #5 rs1=3; rs2=5; rd=10; func=0; addr=125; //ADD
  #20 rs1=3; rs2=8; rd=12; func=2; addr=126; //MUL
  #20 rs1=10; rs2=5; rd=14; func=1; addr=128; //SUB
  #20 rs1=7; rs2=3; rd=13; func=11; addr=127; //SLA
  #20 rs1=10; rs2=5; rd=15; func=1; addr=129; //SUB
  #20 rs1=12; rs2=13; rd=16; func=0; addr=130; //ADD
  #60 for(k=125;k<131;k=k+1)
    $display("mem[%3d]=53d", k, MYPIPE.mem[k]);
 end
initial 
 begin
  $dumpfile("ass_2.vcd");
  $dumpvars(0,ass_2_tb);
  $monitor("time: %3d,F=%3d",$time,z);
  #300 $finish;
 end
endmodule



module ass_2(zout,rs1,rs2,rd,func,addr,clk1,clk2);
input [3:0]rs1,rs2,rd,func;
input  clk1,clk2;
input [7:0]addr;
output [15:0] zout;

reg [15:0] L12_A,L12_B,L23_Z,L34_Z;
reg[3:0] L12_rd,L12_func,L23_rd;
reg[7:0] L12_addr,L23_addr,L34_addr;
reg[15:0] regbank [0:15];
reg [15:0] mem[0:255];
assign zout=L34_Z;

always @(posedge clk1)
begin
 L12_A<= #2  regbank[rs1];
 L12_B<= #2 regbank[rs2];
 L12_rd<= #2 rd;
 L12_func<= #2 func;
 L12_addr<= #2 addr;
end

always @(negedge clk2)
begin
 case(func)
  0: L23_Z <= #2 L12_A+L12_B;
  1: L23_Z <= #2 L12_A-L12_B;
  2: L23_Z <= #2 L12_A*L12_B;
  3: L23_Z <= #2 L12_A;
  4: L23_Z <= #2 L12_B;
  5: L23_Z <= #2 L12_A & L12_B;
  6: L23_Z <= #2 L12_A | L12_B;
  7: L23_Z <= #2 L12_A ^ L12_B;
  8: L23_Z <= #2  ~ L12_A;
  9: L23_Z <= #2  ~ L12_B;
  10: L23_Z <= #2 L12_A >> 1;
  11: L23_Z <= #2 L12_A << 1;
  default : L23_Z <= #2 16'hxxxx;
 endcase
  L23_rd <=#2 L12_rd;
  L23_addr <=#2 L12_addr;
end
 always @(posedge clk1)
  begin
   regbank [L23_rd] <= #2 L23_Z;
   L34_Z<= #2 L23_Z;
   L34_addr<= #2 L23_addr;
  end
  always @(negedge clk2)
   begin
    mem[L34_addr]<=#2 L34_Z;
   end
endmodule

ass_2/ass_2.vcd
$date
    Mar 26, 2022  09:25:57
$end
$version
    TOOL:	ncsim(64)	15.20-s051
$end
$timescale
    1 ns
$end

$scope module ass_2_tb $end
$var wire     16 !    z [15:0] $end
$var reg       4 "    rs1 [3:0] $end
$var reg       4 #    rs2 [3:0] $end
$var reg       4 $    rd [3:0] $end
$var reg       4 %    func [3:0] $end
$var reg       8 &    addr [7:0] $end
$var reg       1 '    clk1  $end
$var reg       1 (    clk2  $end
$var integer  32 )    k  $end

$scope module MYPIPE $end
$var wire      4 *    rs1 [3:0] $end
$var wire      4 +    rs2 [3:0] $end
$var wire      4 ,    rd [3:0] $end
$var wire      4 -    func [3:0] $end
$var wire      1 .    clk1  $end
$var wire      1 /    clk2  $end
$var wire      8 0    addr [7:0] $end
$var wire     16 !    zout [15:0] $end
$var reg      16 1    L12_A [15:0] $end
$var reg      16 2    L12_B [15:0] $end
$var reg      16 3    L23_Z [15:0] $end
$var reg      16 4    L34_Z [15:0] $end
$var reg       4 5    L12_rd [3:0] $end
$var reg       4 6    L12_func [3:0] $end
$var reg       4 7    L23_rd [3:0] $end
$var reg       8 8    L12_addr [7:0] $end
$var reg       8 9    L23_addr [7:0] $end
$var reg       8 :    L34_addr [7:0] $end
$upscope $end

$upscope $end

$enddefinitions $end
$dumpvars
bx !
bx "
bx #
bx $
bx %
bx &
0'
0(
b10000 )
bx *
bx +
bx ,
bx -
0.
0/
b0xxxx 0
bx 1
bx 2
bx 3
bx 4
bx 5
bx 6
bx 7
bx 8
bx 9
bx :
$end
#5
1'
b11 "
b101 #
b1010 $
b0 %
b1111101 &
b1101 -
b0 0
b1010 ,
b101 +
b11 *
1.
#7
b11 1
b101 2
b1010 5
b1101 6
b0 8
#10
0'
0.
#15
1(
1/
#20
0(
0/
#22
b1010 7
b0 9
#25
b1000 #
b1100 $
b10 %
b1111110 &
1'
1.
b1110 -
b10 0
b1100 ,
b1000 +
#27
b0 :
b1000 2
b1100 5
b1110 6
b10 8
#30
0'
0.
#35
1(
1/
#40
0(
0/
#42
b1100 7
b10 9
#45
b1010 "
b101 #
b1110 $
b1 %
b10000000 &
1'
1.
b0 -
b1 0
b1110 ,
b101 +
b1010 *
#47
b10 :
bx 1
b101 2
b1110 5
b0 6
b1 8
#50
0'
0.
#55
1(
1/
#60
0(
0/
#62
b1110 7
b1 9
#65
b111 "
b11 #
b1101 $
b1011 %
b1111111 &
1'
1.
b1111 -
b1011 0
b1101 ,
b11 +
b111 *
#67
b1 :
b111 1
b11 2
b1101 5
b1111 6
b1011 8
#70
0'
0.
#75
1(
1/
#80
0(
0/
#82
b1101 7
b1011 9
#85
b1010 "
b101 #
b1111 $
b1 %
b10000001 &
1'
1.
b1 -
b1 0
b1111 ,
b101 +
b1010 *
#87
b1011 :
bx 1
b101 2
b1111 5
b1 6
b1 8
#90
0'
0.
#95
1(
1/
#100
0(
0/
#102
b1111 7
b1 9
#105
b1100 "
b1101 #
b0 $
b0 %
b10000010 &
1'
1.
b10 -
b0 0
b0 ,
b1101 +
b1100 *
#107
b1 :
bx 2
b0 5
b10 6
b0 8
#110
0'
0.
#115
1(
1/
#120
0(
0/
#122
b0 7
b0 9
#125
1'
1.
#127
b0 :
#130
0'
0.
#135
1(
1/
#140
0(
0/
#145
1'
1.
#150
0'
0.
#155
1(
1/
#160
0(
0/
#165
b1111101 )
b1111110 )
b1111111 )
b10000000 )
b10000001 )
b10000010 )
b10000011 )
1'
1.
